nephelai/__init__.py
nephelai/api.py
nephelai/main.py
nephelai/py.typed
nephelai-0.2.0.dist-info/entry_points.txt
nephelai-0.2.0.dist-info/LICENSE
nephelai-0.2.0.dist-info/WHEEL
nephelai-0.2.0.dist-info/METADATA
nephelai-0.2.0.dist-info/RECORD
