Metadata-Version: 2.1
Name: nephelai
Version: 0.2.0
Summary: A helper library to transport your data into the (next)cloud
Home-page: https://github.com/dobraczka/nephelai
License: MIT
Keywords: nextcloud,mlops
Author: Daniel Obraczka
Author-email: obraczka@informatik.uni-leipzig.de
Requires-Python: >=3.8,<4.0
Classifier: Development Status :: 4 - Beta
Classifier: License :: OSI Approved :: MIT License
Classifier: Programming Language :: Python
Classifier: Programming Language :: Python :: 3
Classifier: Programming Language :: Python :: 3.8
Classifier: Programming Language :: Python :: 3.9
Classifier: Programming Language :: Python :: 3.10
Classifier: Programming Language :: Python :: 3.11
Classifier: Programming Language :: Python :: 3 :: Only
Classifier: Programming Language :: Python :: 3.10
Classifier: Programming Language :: Python :: 3.8
Classifier: Programming Language :: Python :: 3.9
Provides-Extra: docs
Requires-Dist: bitmath (>=1.3.3.1,<2.0.0.0)
Requires-Dist: mkdocs (>=1.4.2,<2.0.0) ; extra == "docs"
Requires-Dist: mkdocs-gen-files (>=0.4.0,<0.5.0) ; extra == "docs"
Requires-Dist: mkdocs-literate-nav (>=0.6.0,<0.7.0) ; extra == "docs"
Requires-Dist: mkdocs-material (>=9.0.9,<10.0.0) ; extra == "docs"
Requires-Dist: mkdocs-section-index (>=0.3.5,<0.4.0) ; extra == "docs"
Requires-Dist: mkdocstrings[python] (>=0.20.0,<0.21.0) ; extra == "docs"
Requires-Dist: pyocclient (>=0.6,<0.7)
Requires-Dist: python-dotenv (>=1.0.0,<2.0.0)
Requires-Dist: tqdm (>=4.65.0,<5.0.0)
Requires-Dist: typer (>=0.9.0,<0.10.0)
Requires-Dist: typing-extensions (>=4.7.1,<5.0.0)
Project-URL: Bug Tracker, https://github.com/dobraczka/nephelai/issues
Project-URL: Documentation, https://nephelai.readthedocs.io
Project-URL: Repository, https://github.com/dobraczka/nephelai
Project-URL: Source, https://github.com/dobraczka/nephelai
